llm_cache/__init__.py
llm_cache/cli.py
llm_cache/core/cache.py
llm_cache/core/encryption.py
llm_cache/core/hashing.py
llm_cache/core/pricing.py
llm_cache/core/schema.py
llm_cache/core/streaming.py
llm_cache/core/backends/__init__.py
llm_cache/core/backends/sqlite_backend.py
llm_cache/integrations/__init__.py
llm_cache/integrations/http_proxy.py
llm_cache/integrations/openai_wrap.py
llm_cache/utils/__init__.py
llm_cache/utils/config.py
llm_cache_pro-0.1.2.dist-info/METADATA
llm_cache_pro-0.1.2.dist-info/WHEEL
llm_cache_pro-0.1.2.dist-info/entry_points.txt
llm_cache_pro-0.1.2.dist-info/licenses/LICENSE
llm_cache_pro-0.1.2.dist-info/RECORD
