Metadata-Version: 2.4
Name: llm-cache-pro
Version: 0.1.2
Summary: A drop-in, model-agnostic cache for Large Language Model API calls
Project-URL: Homepage, https://sherin-sef-ai.github.io/
Project-URL: Repository, https://github.com/Sherin-SEF-AI/llm-cache.git
Project-URL: Documentation, https://github.com/Sherin-SEF-AI/llm-cache
Project-URL: Bug Tracker, https://github.com/Sherin-SEF-AI/llm-cache/issues
Author-email: Sherin Joseph Roy <sherin.joseph2217@gmail.com>
License: MIT
License-File: LICENSE
Classifier: Development Status :: 4 - Beta
Classifier: Intended Audience :: Developers
Classifier: License :: OSI Approved :: MIT License
Classifier: Operating System :: OS Independent
Classifier: Programming Language :: Python :: 3
Classifier: Programming Language :: Python :: 3.10
Classifier: Programming Language :: Python :: 3.11
Classifier: Programming Language :: Python :: 3.12
Classifier: Topic :: Internet :: WWW/HTTP :: HTTP Servers
Classifier: Topic :: Software Development :: Libraries :: Python Modules
Requires-Python: >=3.10
Requires-Dist: cryptography>=41.0.0
Requires-Dist: fastapi>=0.104.0
Requires-Dist: httpx>=0.25.0
Requires-Dist: orjson>=3.9.0
Requires-Dist: pydantic>=2.0.0
Requires-Dist: python-multipart>=0.0.6
Requires-Dist: redis>=5.0.0
Requires-Dist: rich>=13.0.0
Requires-Dist: sqlmodel>=0.0.8
Requires-Dist: toml>=0.10.2
Requires-Dist: typer[all]>=0.9.0
Requires-Dist: uvicorn[standard]>=0.24.0
Requires-Dist: zstandard>=0.21.0
Provides-Extra: dev
Requires-Dist: black>=23.0.0; extra == 'dev'
Requires-Dist: pre-commit>=3.5.0; extra == 'dev'
Requires-Dist: pytest-asyncio>=0.21.0; extra == 'dev'
Requires-Dist: pytest-cov>=4.1.0; extra == 'dev'
Requires-Dist: pytest>=7.4.0; extra == 'dev'
Requires-Dist: ruff>=0.1.0; extra == 'dev'
